laoyanjing/__init__.py
laoyanjing-0.1.0.dist-info/WHEEL
laoyanjing-0.1.0.dist-info/entry_points.txt
laoyanjing-0.1.0.dist-info/METADATA
laoyanjing-0.1.0.dist-info/RECORD
