Metadata-Version: 2.3
Name: laoyanjing
Version: 0.1.0
Summary: Add your description here
Author: laoyanjing
Author-email: laoyanjing <2916628814@qq.com>
Requires-Dist: mcp[cli]>=1.12.2
Requires-Python: >=3.13
